state/__init__.py
state/__main__.py
state/py.typed
state/_cli/__init__.py
state/_cli/_emb/__init__.py
state/_cli/_emb/_eval.py
state/_cli/_emb/_fit.py
state/_cli/_emb/_preprocess.py
state/_cli/_emb/_query.py
state/_cli/_emb/_transform.py
state/_cli/_tx/__init__.py
state/_cli/_tx/_infer.py
state/_cli/_tx/_predict.py
state/_cli/_tx/_preprocess_infer.py
state/_cli/_tx/_preprocess_train.py
state/_cli/_tx/_train.py
state/configs/__init__.py
state/configs/config.yaml
state/configs/state-defaults.yaml
state/configs/data/default.yaml
state/configs/data/perturbation.yaml
state/configs/model/celltypemean.yaml
state/configs/model/context_mean.yaml
state/configs/model/cpa.yaml
state/configs/model/decoder_only.yaml
state/configs/model/embedsum.yaml
state/configs/model/globalsimplesum.yaml
state/configs/model/old_neuralot.yaml
state/configs/model/pertsets.yaml
state/configs/model/perturb_mean.yaml
state/configs/model/pseudobulk.yaml
state/configs/model/scgpt-chemical.yaml
state/configs/model/scgpt-genetic.yaml
state/configs/model/scvi.yaml
state/configs/model/state.yaml
state/configs/model/state_lg.yaml
state/configs/model/state_sm.yaml
state/configs/model/tahoe_best.yaml
state/configs/model/tahoe_llama_212693232.yaml
state/configs/model/tahoe_llama_62089464.yaml
state/configs/training/cpa.yaml
state/configs/training/default.yaml
state/configs/training/scgpt.yaml
state/configs/training/scvi.yaml
state/emb/__init__.py
state/emb/finetune_decoder.py
state/emb/inference.py
state/emb/utils.py
state/emb/vectordb.py
state/emb/data/__init__.py
state/emb/data/loader.py
state/emb/eval/__init__.py
state/emb/eval/emb.py
state/emb/nn/__init__.py
state/emb/nn/eval_utils.py
state/emb/nn/flash_transformer.py
state/emb/nn/loss.py
state/emb/nn/model.py
state/emb/tools/__init__.py
state/emb/tools/slurm.py
state/emb/train/__init__.py
state/emb/train/__main__.py
state/emb/train/callbacks.py
state/emb/train/trainer.py
state/tx/__init__.py
state/tx/callbacks/__init__.py
arc_state-0.10.2.dist-info/METADATA
arc_state-0.10.2.dist-info/WHEEL
arc_state-0.10.2.dist-info/entry_points.txt
arc_state-0.10.2.dist-info/licenses/LICENSE
arc_state-0.10.2.dist-info/RECORD
