Metadata-Version: 2.4
Name: arc-state
Version: 0.10.2
Summary: State is a machine learning model that predicts cellular perturbation response across diverse contexts.
Author-email: Abhinav Adduri <abhinav.adduri@arcinstitute.org>, Yusuf Roohani <yusuf.roohani@arcinstitute.org>, Noam Teyssier <noam.teyssier@arcinstitute.org>, Rajesh Ilango <rilango@gmail.com>, Dhruv Gautam <dhruvgautam@berkeley.edu>
License-File: LICENSE
Requires-Python: <3.13,>=3.10
Requires-Dist: anndata>=0.11.4
Requires-Dist: cell-eval>=0.6.8
Requires-Dist: cell-load>=0.8.7
Requires-Dist: geomloss>=0.2.6
Requires-Dist: hydra-core>=1.3.2
Requires-Dist: ipykernel>=6.30.1
Requires-Dist: numpy>=2.2.6
Requires-Dist: pandas>=2.2.3
Requires-Dist: peft>=0.11.0
Requires-Dist: pyyaml>=6.0.2
Requires-Dist: scanpy>=1.11.2
Requires-Dist: scikit-learn>=1.6.1
Requires-Dist: scipy>=1.15.0
Requires-Dist: seaborn>=0.13.2
Requires-Dist: torch>=2.7.0
Requires-Dist: tqdm>=4.67.1
Requires-Dist: transformers>=4.52.3
Requires-Dist: wandb>=0.19.11
Provides-Extra: vectordb
Requires-Dist: lancedb>=0.24.0; extra == 'vectordb'
